mahdi_env/__init__.py
mahdi_env/env.py
mahdi_env-2.0.0.dist-info/METADATA
mahdi_env-2.0.0.dist-info/WHEEL
mahdi_env-2.0.0.dist-info/RECORD
