Metadata-Version: 2.3
Name: mahdi_env
Version: 2.0.0
Summary: SSGAC Environment VARs
Author-email: Mahdi Mir <imahdimir@gmail.com>
